odoo/addons/theme_kaizen/README.rst
odoo/addons/theme_kaizen/__init__.py
odoo/addons/theme_kaizen/__manifest__.py
odoo/addons/theme_kaizen/i18n/theme_kaizen.pot
odoo/addons/theme_kaizen/readme/CONTRIBUTORS.rst
odoo/addons/theme_kaizen/readme/CREDITS.rst
odoo/addons/theme_kaizen/readme/DESCRIPTION.rst
odoo/addons/theme_kaizen/readme/ROADMAP.rst
odoo/addons/theme_kaizen/static/description/devices.png
odoo/addons/theme_kaizen/static/description/faq.png
odoo/addons/theme_kaizen/static/description/hero.png
odoo/addons/theme_kaizen/static/description/icon.png
odoo/addons/theme_kaizen/static/description/index.html
odoo/addons/theme_kaizen/static/description/latest-news.png
odoo/addons/theme_kaizen/static/description/main.gif
odoo/addons/theme_kaizen/static/description/menu-1.png
odoo/addons/theme_kaizen/static/description/menu-2.png
odoo/addons/theme_kaizen/static/description/menu-3.png
odoo/addons/theme_kaizen/static/description/poster.png
odoo/addons/theme_kaizen/static/description/swiper.png
odoo/addons/theme_kaizen/static/font/Ubuntu-Bold.ttf
odoo/addons/theme_kaizen/static/font/Ubuntu-Light.ttf
odoo/addons/theme_kaizen/static/font/UbuntuMono-Regular.ttf
odoo/addons/theme_kaizen/static/img/header/community-banner.jpg
odoo/addons/theme_kaizen/static/img/homepage/Fairphone.svg
odoo/addons/theme_kaizen/static/img/homepage/Nexus.svg
odoo/addons/theme_kaizen/static/img/homepage/OnePlusOne.svg
odoo/addons/theme_kaizen/static/img/homepage/PinePhone.svg
odoo/addons/theme_kaizen/static/img/homepage/Volla.svg
odoo/addons/theme_kaizen/static/img/homepage/hero.jpg
odoo/addons/theme_kaizen/static/img/homepage/media-1-mobile.jpg
odoo/addons/theme_kaizen/static/img/homepage/media-2-mobile.jpg
odoo/addons/theme_kaizen/static/img/icons/angle-icon-gradient.svg
odoo/addons/theme_kaizen/static/img/icons/angle-icon.svg
odoo/addons/theme_kaizen/static/img/icons/bullet-gradient.svg
odoo/addons/theme_kaizen/static/img/icons/calendar.svg
odoo13_addon_theme_kaizen-13.0.1.0.1.dev4.dist-info/METADATA
odoo13_addon_theme_kaizen-13.0.1.0.1.dev4.dist-info/WHEEL
odoo13_addon_theme_kaizen-13.0.1.0.1.dev4.dist-info/top_level.txt
odoo13_addon_theme_kaizen-13.0.1.0.1.dev4.dist-info/RECORD
